nmk_github/__init__.py
nmk_github/action.py
nmk_github/action.yml
nmk_github/badges.yml
nmk_github/info.py
nmk_github/plugin.yml
nmk_github/templates/__init__.py
nmk_github/templates/build.yml
nmk_github-1.0.1.dist-info/licenses/LICENSE
nmk_github-1.0.1.dist-info/METADATA
nmk_github-1.0.1.dist-info/WHEEL
nmk_github-1.0.1.dist-info/top_level.txt
nmk_github-1.0.1.dist-info/RECORD
